pymysqleasy/MysqlDB.py
pymysqleasy/__init__.py
pymysqleasy-1.0.1.dist-info/LICENSE
pymysqleasy-1.0.1.dist-info/METADATA
pymysqleasy-1.0.1.dist-info/WHEEL
pymysqleasy-1.0.1.dist-info/top_level.txt
pymysqleasy-1.0.1.dist-info/RECORD
